tap_linkedin_ads/__init__.py
tap_linkedin_ads/client.py
tap_linkedin_ads/streams.py
tap_linkedin_ads/tap.py
meltano_tap_linkedin_ads-0.0.1a2.dist-info/LICENSE
meltano_tap_linkedin_ads-0.0.1a2.dist-info/METADATA
meltano_tap_linkedin_ads-0.0.1a2.dist-info/WHEEL
meltano_tap_linkedin_ads-0.0.1a2.dist-info/entry_points.txt
meltano_tap_linkedin_ads-0.0.1a2.dist-info/RECORD
