Metadata-Version: 2.1
Name: meltano-tap-linkedin-ads
Version: 0.0.1a2
Summary: `tap-linkedin-ads` is a Singer tap for linkedin, built with the Meltano SDK for Singer Taps.
License: Elastic-2.0
Keywords: ELT,linkedin
Author: Meltano
Author-email: hello@meltano.com
Requires-Python: >=3.7.1,<3.12
Classifier: License :: Other/Proprietary License
Classifier: Programming Language :: Python :: 3
Classifier: Programming Language :: Python :: 3.8
Classifier: Programming Language :: Python :: 3.9
Classifier: Programming Language :: Python :: 3.10
Classifier: Programming Language :: Python :: 3.11
Requires-Dist: pendulum (>=2.1.2,<3.0.0)
Requires-Dist: requests (>=2.31.0,<3.0.0)
Requires-Dist: singer-sdk (>=0.27.0,<0.28.0)
